[
  {
    "anonymous": false,
    "inputs": [
      {
        "indexed": true,
        "internalType": "bytes32",
        "name": "pactid",
        "type": "bytes32"
      },
      {
        "indexed": false,
        "internalType": "uint256",
        "name": "value",
        "type": "uint256"
      },
      {
        "indexed": true,
        "internalType": "address",
        "name": "payer",
        "type": "address"
      }
    ],
    "name": "LogPaymentMade",
    "type": "event"
  },
  {
    "anonymous": false,
    "inputs": [
      {
        "indexed": true,
        "internalType": "bytes32",
        "name": "pactid",
        "type": "bytes32"
      },
      {
        "indexed": false,
        "internalType": "enum PactState",
        "name": "newState",
        "type": "uint8"
      },
      {
        "indexed": true,
        "internalType": "address",
        "name": "updater",
        "type": "address"
      }
    ],
    "name": "LogStateUpdate",
    "type": "event"
  }
]
